Metadata-Version: 2.1
Name: robotframework-parrot-dtmf
Version: 1.0.2
Summary: DTMF (Dual tone multi frequency) Library used to generate and verify DTMF tone
Home-page: https://github.com/zilogic-systems/parrot
Author: Zilogic Systems
Author-email: code@zilogic.com
Classifier: Programming Language :: Python :: 3
Requires-Python: >=3.6
License-File: LICENSE
Requires-Dist: pydub
Requires-Dist: numpy
Requires-Dist: robotframework
